{"version":1,"document":[{"__type__":"cc.AnimationClip","_name":"monster12","_objFlags":0,"__editorExtras__":{"embeddedPlayerGroups":[]},"_native":"","sample":25,"speed":1,"wrapMode":2,"enableTrsBlending":false,"_duration":0.4,"_hash":500763545,"_tracks":[{"__id__":1}],"_exoticAnimation":null,"_events":[],"_embeddedPlayers":[],"_additiveSettings":{"__id__":6},"_auxiliaryCurveEntries":[]},{"__type__":"cc.animation.ObjectTrack","_binding":{"__type__":"cc.animation.TrackBinding","path":{"__id__":2},"proxy":null},"_channel":{"__id__":4}},{"__type__":"cc.animation.TrackPath","_paths":[{"__id__":3},"spriteFrame"]},{"__type__":"cc.animation.ComponentPath","component":"cc.Sprite"},{"__type__":"cc.animation.Channel","_curve":{"__id__":5}},{"__type__":"cc.ObjectCurve","_times":[0,0.04,0.08,0.12,0.16,0.2,0.24,0.28,0.32,0.36],"_values":[{"__uuid__":"f4QfUunCRKbrVTdK/i0ml1@f9941","__expectedType__":"cc.Asset"},{"__uuid__":"ddyFWR+qdKo6xchL6iLmxH@f9941","__expectedType__":"cc.Asset"},{"__uuid__":"20EqkVh1hGdKoET1+5W1JA@f9941","__expectedType__":"cc.Asset"},{"__uuid__":"20PM4wY3BG2Yasn3QOy3ER@f9941","__expectedType__":"cc.Asset"},{"__uuid__":"5ftV/YflpFlLD6IUz1eVXx@f9941","__expectedType__":"cc.Asset"},{"__uuid__":"52H8Giu0dOLISpiHX4Q3q6@f9941","__expectedType__":"cc.Asset"},{"__uuid__":"52d47bsdhPwopuDemJFOYQ@f9941","__expectedType__":"cc.Asset"},{"__uuid__":"db51zeXJlCoroOVfouC0D0@f9941","__expectedType__":"cc.Asset"},{"__uuid__":"cbN1ASFL5Dwp3l6mO1oReq@f9941","__expectedType__":"cc.Asset"},{"__uuid__":"7dL2xr545JXa562QOqogNH@f9941","__expectedType__":"cc.Asset"}]},{"__type__":"cc.AnimationClipAdditiveSettings","enabled":false,"refClip":null}],"chunks":[]}
