{"version":1,"document":[{"__type__":"cc.AnimationClip","_name":"monster9","_objFlags":0,"__editorExtras__":{"embeddedPlayerGroups":[]},"_native":"","sample":25,"speed":1,"wrapMode":2,"enableTrsBlending":false,"_duration":0.4,"_hash":500763545,"_tracks":[{"__id__":1}],"_exoticAnimation":null,"_events":[],"_embeddedPlayers":[],"_additiveSettings":{"__id__":6},"_auxiliaryCurveEntries":[]},{"__type__":"cc.animation.ObjectTrack","_binding":{"__type__":"cc.animation.TrackBinding","path":{"__id__":2},"proxy":null},"_channel":{"__id__":4}},{"__type__":"cc.animation.TrackPath","_paths":[{"__id__":3},"spriteFrame"]},{"__type__":"cc.animation.ComponentPath","component":"cc.Sprite"},{"__type__":"cc.animation.Channel","_curve":{"__id__":5}},{"__type__":"cc.ObjectCurve","_times":[0,0.04,0.08,0.12,0.16,0.2,0.24,0.28,0.32,0.36],"_values":[{"__uuid__":"8aXAa3Zm1D2JKHEEnyuLq2@f9941","__expectedType__":"cc.Asset"},{"__uuid__":"d1nxN23lpAC7XJqdtq8j12@f9941","__expectedType__":"cc.Asset"},{"__uuid__":"b5PCRV+wBBcYYJ45qYZc3J@f9941","__expectedType__":"cc.Asset"},{"__uuid__":"adJPmGUQ1AyoAtisZSkuxp@f9941","__expectedType__":"cc.Asset"},{"__uuid__":"dcQUeKe49EsJM0k86olrcn@f9941","__expectedType__":"cc.Asset"},{"__uuid__":"95EQIc2yRNQI9SvvMTgvoB@f9941","__expectedType__":"cc.Asset"},{"__uuid__":"0ct1prPsNBYrt0UFUyKJXO@f9941","__expectedType__":"cc.Asset"},{"__uuid__":"bfEH8z6plFBLoQbHh2bvMC@f9941","__expectedType__":"cc.Asset"},{"__uuid__":"bePiypPkhIG6ssWhCY1AyJ@f9941","__expectedType__":"cc.Asset"},{"__uuid__":"19A70kLOZCvIsaYXvdx7kM@f9941","__expectedType__":"cc.Asset"}]},{"__type__":"cc.AnimationClipAdditiveSettings","enabled":false,"refClip":null}],"chunks":[]}
